sa_tenders/__init__.py
sa_tenders/adding_variables.py
sa_tenders/data_cleaning.py
sa_tenders/dict_to_dataframe.py
sa_tenders/main.py
sa_tenders/old.py
sa_tenders/test_ideas.py
sa_tenders-0.1.0.dist-info/METADATA
sa_tenders-0.1.0.dist-info/WHEEL
sa_tenders-0.1.0.dist-info/top_level.txt
sa_tenders-0.1.0.dist-info/RECORD
