Metadata-Version: 2.4
Name: sa_tenders
Version: 0.1.0
Summary: This library enables developers to download and process data from the South African etenders platform.
Author: Ntuthuko Hlela
License: MIT License
Requires-Dist: pandas
Requires-Dist: numpy
Requires-Dist: flatdict
Requires-Dist: openpyxl
Requires-Dist: requests
Dynamic: author
Dynamic: description
Dynamic: description-content-type
Dynamic: license
Dynamic: requires-dist
Dynamic: summary
